headless_coder_sdk/core/__init__.py
headless_coder_sdk/core/cancellation.py
headless_coder_sdk/core/registry.py
headless_coder_sdk/core/types.py
headless_coder_sdk_core-0.1.0.dist-info/METADATA
headless_coder_sdk_core-0.1.0.dist-info/WHEEL
headless_coder_sdk_core-0.1.0.dist-info/licenses/LICENSE
headless_coder_sdk_core-0.1.0.dist-info/RECORD
