Metadata-Version: 2.4
Name: headless-coder-sdk-core
Version: 0.1.0
Summary: Core registry, types, and utilities for the headless-coder-sdk Python port.
Project-URL: Homepage, https://github.com/OhadAssulin/headless-coder-sdk
Project-URL: Source, https://github.com/OhadAssulin/python-headless-coder
Author: Ohad Assulin
License: MIT License
License-File: LICENSE
Keywords: ai,claude,codex,gemini,sdk
Classifier: Intended Audience :: Developers
Classifier: License :: OSI Approved :: MIT License
Classifier: Programming Language :: Python :: 3
Classifier: Programming Language :: Python :: 3.9
Requires-Python: >=3.9
Requires-Dist: typing-extensions>=4.9
